sql/__init__.py
pgsql_table-0.5.dist-info/METADATA
pgsql_table-0.5.dist-info/WHEEL
pgsql_table-0.5.dist-info/top_level.txt
pgsql_table-0.5.dist-info/RECORD
